django_postgres_anon/__init__.py
django_postgres_anon/admin.py
django_postgres_anon/admin_base.py
django_postgres_anon/apps.py
django_postgres_anon/config.py
django_postgres_anon/constants.py
django_postgres_anon/context_managers.py
django_postgres_anon/decorators.py
django_postgres_anon/exceptions.py
django_postgres_anon/middleware.py
django_postgres_anon/models.py
django_postgres_anon/utils.py
django_postgres_anon/config/presets/django_auth.yaml
django_postgres_anon/config/presets/ecommerce.yaml
django_postgres_anon/config/presets/education.yaml
django_postgres_anon/config/presets/finance.yaml
django_postgres_anon/config/presets/healthcare.yaml
django_postgres_anon/config/presets/social_media.yaml
django_postgres_anonymizer-0.1.0a1.dist-info/licenses/LICENSE
django_postgres_anonymizer-0.1.0a1.dist-info/METADATA
django_postgres_anonymizer-0.1.0a1.dist-info/WHEEL
django_postgres_anonymizer-0.1.0a1.dist-info/top_level.txt
django_postgres_anonymizer-0.1.0a1.dist-info/RECORD
