Metadata-Version: 2.4
Name: django-postgres-anonymizer
Version: 0.1.0a1
Summary: Django integration for PostgreSQL Anonymizer extension
Author-email: Sanyam Khurana <sanyam@sanyamkhurana.com>
Maintainer-email: Sanyam Khurana <sanyam@sanyamkhurana.com>
License: BSD-3-Clause
Project-URL: Homepage, https://github.com/CuriousLearner/django-postgres-anonymizer
Project-URL: Documentation, https://django-postgres-anonymizer.readthedocs.io/
Project-URL: Repository, https://github.com/CuriousLearner/django-postgres-anonymizer
Project-URL: Bug Tracker, https://github.com/CuriousLearner/django-postgres-anonymizer/issues
Project-URL: Changelog, https://github.com/CuriousLearner/django-postgres-anonymizer/blob/main/CHANGELOG.md
Keywords: django,postgresql,anonymization,privacy,gdpr,database,security
Classifier: Development Status :: 3 - Alpha
Classifier: Environment :: Web Environment
Classifier: Framework :: Django
Classifier: Framework :: Django :: 3.2
Classifier: Framework :: Django :: 4.0
Classifier: Framework :: Django :: 4.1
Classifier: Framework :: Django :: 4.2
Classifier: Framework :: Django :: 5.0
Classifier: Intended Audience :: Developers
Classifier: License :: OSI Approved :: BSD License
Classifier: Operating System :: OS Independent
Classifier: Programming Language :: Python
Classifier: Programming Language :: Python :: 3
Classifier: Programming Language :: Python :: 3.8
Classifier: Programming Language :: Python :: 3.9
Classifier: Programming Language :: Python :: 3.10
Classifier: Programming Language :: Python :: 3.11
Classifier: Programming Language :: Python :: 3.12
Classifier: Topic :: Database
Classifier: Topic :: Internet :: WWW/HTTP
Classifier: Topic :: Security
Classifier: Topic :: Software Development :: Libraries :: Python Modules
Classifier: Topic :: Utilities
Requires-Python: >=3.8
License-File: LICENSE
Requires-Dist: Django>=3.2
Requires-Dist: psycopg2-binary>=2.8.0
Requires-Dist: PyYAML>=5.4.0
Provides-Extra: test
Requires-Dist: pytest>=7.0.0; extra == "test"
Requires-Dist: pytest-django>=4.5.0; extra == "test"
Requires-Dist: pytest-cov>=4.0.0; extra == "test"
Requires-Dist: pytest-env>=0.8.0; extra == "test"
Requires-Dist: pytest-xdist>=3.0.0; extra == "test"
Requires-Dist: coverage>=6.0.0; extra == "test"
Requires-Dist: model-bakery>=1.20.0; extra == "test"
Provides-Extra: dev
Requires-Dist: django-postgres-anonymizer[test]; extra == "dev"
Requires-Dist: black>=22.0.0; extra == "dev"
Requires-Dist: isort>=5.10.0; extra == "dev"
Requires-Dist: flake8>=5.0.0; extra == "dev"
Requires-Dist: ruff>=0.8.0; extra == "dev"
Requires-Dist: mypy>=0.990; extra == "dev"
Requires-Dist: bandit>=1.7.0; extra == "dev"
Requires-Dist: safety>=2.0.0; extra == "dev"
Requires-Dist: twine>=4.0.0; extra == "dev"
Requires-Dist: build>=0.8.0; extra == "dev"
Requires-Dist: pre-commit>=3.5.0; extra == "dev"
Dynamic: license-file
